.coveragerc
.stestr.conf
AUTHORS
CONTRIBUTING.rst
ChangeLog
HACKING.rst
LICENSE
README.rst
babel.cfg
requirements.txt
setup.cfg
setup.py
test-requirements.txt
tox.ini
build_scripts/build-rhel-packages-inner.sh
build_scripts/build-rhel-packages.sh
build_scripts/is_version_bumped.py
build_scripts/openstack_python_arista_ccf_neutronclient.build
build_scripts/openstack_python_arista_ccf_neutronclient_pull_req.build
build_scripts/precheckin.sh
build_scripts/upload_to_pypi.sh
doc/source/conf.py
doc/source/index.rst
doc/source/readme.rst
doc/source/admin/index.rst
doc/source/cli/index.rst
doc/source/configuration/index.rst
doc/source/contributor/contributing.rst
doc/source/contributor/index.rst
doc/source/install/common_configure.rst
doc/source/install/common_prerequisites.rst
doc/source/install/get_started.rst
doc/source/install/index.rst
doc/source/install/install-obs.rst
doc/source/install/install-rdo.rst
doc/source/install/install-ubuntu.rst
doc/source/install/install.rst
doc/source/install/next-steps.rst
doc/source/install/verify.rst
doc/source/library/index.rst
doc/source/reference/index.rst
doc/source/user/index.rst
python_arista_ccf_neutronclient/__init__.py
python_arista_ccf_neutronclient.egg-info/PKG-INFO
python_arista_ccf_neutronclient.egg-info/SOURCES.txt
python_arista_ccf_neutronclient.egg-info/dependency_links.txt
python_arista_ccf_neutronclient.egg-info/entry_points.txt
python_arista_ccf_neutronclient.egg-info/not-zip-safe
python_arista_ccf_neutronclient.egg-info/pbr.json
python_arista_ccf_neutronclient.egg-info/requires.txt
python_arista_ccf_neutronclient.egg-info/top_level.txt
python_arista_ccf_neutronclient/neutron/__init__.py
python_arista_ccf_neutronclient/neutron/arista_ccf_plugin_client.py
python_arista_ccf_neutronclient/osc/__init__.py
python_arista_ccf_neutronclient/osc/plugin.py
python_arista_ccf_neutronclient/osc/v2/__init__.py
python_arista_ccf_neutronclient/osc/v2/topology/__init__.py
python_arista_ccf_neutronclient/osc/v2/topology/topology_sync.py
python_arista_ccf_neutronclient/tests/__init__.py
python_arista_ccf_neutronclient/tests/base.py
python_arista_ccf_neutronclient/tests/test_python_arista_ccf_neutronclient.py
python_arista_ccf_neutronclient/v2_0/__init__.py
python_arista_ccf_neutronclient/v2_0/client.py
releasenotes/notes/.placeholder
releasenotes/source/conf.py
releasenotes/source/index.rst
releasenotes/source/unreleased.rst
