Metadata-Version: 1.1
Name: python-arista-ccf-neutronclient
Version: 0.1.1
Summary: Python bindings for Arista Networks Converged Cloud Fabric Neutron API
Home-page: http://www.arista.com/
Author: Arista Networks
Author-email: support@arista.com
License: ASL 2.0
Platform: UNKNOWN
Classifier: Environment :: OpenStack
Classifier: Intended Audience :: Information Technology
Classifier: Intended Audience :: System Administrators
Classifier: License :: OSI Approved :: Apache Software License
Classifier: Operating System :: POSIX :: Linux
Classifier: Programming Language :: Python
Classifier: Programming Language :: Python :: 2
Classifier: Programming Language :: Python :: 2.7
Classifier: Programming Language :: Python :: 3
Classifier: Programming Language :: Python :: 3.6
